{
    "id": "70000",
    "meta": {
        "profile": [
            "https://fhir.nhs.uk/STU3/StructureDefinition/eRS-Appointment-1",
            "https://fhir.hl7.org.uk/STU3/StructureDefinition/CareConnect-Appointment-1"
        ]
    },
    "language": "en",
    "resourceType": "Appointment",
    "status": "booked",
    "description": "e-Referral Appointment",
    "start": "2021-02-09T09:00:00.000Z",
    "end": "2021-02-09T09:30:00.000Z",
    "slot": [
        {
            "reference": "Slot/228385"
        }
    ],
    "created": "2021-02-01T14:42:50.584Z",
    "incomingReferral": [
        {
            "reference": "ReferralRequest/000000070002/_history/5"
        }
    ],
    "participant": [
        {
            "actor": {
                "display": "R68-Appointment-DBS",
                "identifier": {
                    "system": "http://fhir.nhs.net/Id/ers-service",
                    "value": "70000"
                }
            },
            "status": "accepted"
        },
        {
            "actor": {
                "identifier": {
                    "system": "http://fhir.nhs.net/Id/nhs-number",
                    "value": "9401130264"
                }
            },
            "status": "accepted"
        }
    ]